{
    "function": "clamp",
    "asm": [
        {
            "type": [
                "float",
                "float",
                "float"
            ],
            "instr": [
                "movaps %xmm0,%xmm3",
                "movaps %xmm2,%xmm0",
                "movaps %xmm1,%xmm4",
                "cmpltps %xmm1,%xmm0",
                "blendvps %xmm0,%xmm2,%xmm4",
                "blendvps %xmm0,%xmm1,%xmm2",
                "maxps %xmm4,%xmm3",
                "movaps %xmm3,%xmm0",
                "minps %xmm2,%xmm0"
            ]
        },
        {
            "type": [
                "double",
                "double",
                "double"
            ],
            "instr": [
                "movapd %xmm0,%xmm3",
                "movapd %xmm2,%xmm0",
                "movapd %xmm1,%xmm4",
                "cmpltpd %xmm1,%xmm0",
                "blendvpd %xmm0,%xmm2,%xmm4",
                "blendvpd %xmm0,%xmm1,%xmm2",
                "maxpd %xmm4,%xmm3",
                "movapd %xmm3,%xmm0",
                "minpd %xmm2,%xmm0"
            ]
        },
        {
            "type": [
                "int",
                "int",
                "int"
            ],
            "instr": [
                "movdqa %xmm0,%xmm3",
                "movdqa %xmm1,%xmm0",
                "movdqa %xmm1,%xmm4",
                "pcmpgtd %xmm2,%xmm0",
                "pblendvb %xmm0,%xmm2,%xmm4",
                "pblendvb %xmm0,%xmm1,%xmm2",
                "movdqa %xmm3,%xmm0",
                "pmaxsd %xmm4,%xmm0",
                "pminsd %xmm2,%xmm0"
            ]
        }
    ]
}